{
  "map": [{"slug":"bone-scythe","name":"Bone Scythe","rarity":"1","children":[{"slug":"bone-scythe-plus","name":"Bone Scythe+","rarity":"2","children":[{"slug":"chief-scythe","name":"Chief Scythe","rarity":"2","children":[{"slug":"bladed-edge","name":"Bladed Edge","rarity":"4","children":[{"slug":"bladed-edge-plus","name":"Bladed Edge+","rarity":"5","children":[{"slug":"limb-cutter","name":"Limb Cutter","rarity":"7","children":[{"slug":"carmine-edge","name":"Carmine Edge","rarity":"9","children":[{"slug":"red-rippers","name":"Red Rippers","rarity":"10","children":[]}]}]}]}]},{"slug":"cutlass","name":"Cutlass","rarity":"3","children":[{"slug":"cutlass-plus","name":"Cutlass+","rarity":"5","children":[],"element":"water"}],"element":"water"},{"slug":"twin-kut-ku","name":"Twin Kut-Ku","rarity":"2","children":[{"slug":"pink-maracas","name":"Pink Maracas","rarity":"3","children":[{"slug":"pink-maracas-plus","name":"Pink Maracas+","rarity":"4","children":[{"slug":"funky-maracas","name":"Funky Maracas","rarity":"6","children":[{"slug":"jungle-maracas","name":"Jungle Maracas","rarity":"9","children":[{"slug":"evergreen","name":"Evergreen","rarity":"9","children":[]}]}]}]}]},{"slug":"twin-kut-ku-plus","name":"Twin Kut-Ku+","rarity":"4","children":[{"slug":"dual-kut-ku","name":"Dual Kut-Ku","rarity":"6","children":[],"element":"fire"}],"element":"fire"},{"slug":"raven-tessen","name":"Raven Tessen","rarity":"5","children":[{"slug":"wolf-tessen","name":"Wolf Tessen","rarity":"7","children":[{"slug":"crow-tessen","name":"Crow Tessen","rarity":"9","children":[]}]}]}],"element":"fire"}]}]}]},{"slug":"black-twin-daggers","name":"Black Twin Daggers","rarity":"5","children":[{"slug":"fatalis-dual-blades","name":"Fatalis Dual Blades","rarity":"8","children":[{"slug":"fatalis-dual-sky","name":"Fatalis Dual Sky","rarity":"10","children":[],"element":"dragon"}],"element":"dragon"},{"slug":"ultimus-celestials","name":"Ultimus Celestials","rarity":"8","children":[{"slug":"ultimus-apocalypse","name":"Ultimus Apocalypse","rarity":"10","children":[],"element":"dragon"}],"element":"dragon"}],"element":"dragon"},{"slug":"flaming-pair","name":"Flaming Pair","rarity":"5","children":[{"slug":"crimson-lotus-blades","name":"Crimson Lotus Blades","rarity":"8","children":[{"slug":"demonic-flaming-pair","name":"Demonic Flaming Pair","rarity":"9","children":[{"slug":"azure-dual-swords","name":"Azure Dual Swords","rarity":"10","children":[],"element":"dragon"}],"element":"dragon"}],"element":"dragon"}],"element":"dragon"},{"slug":"worn-blades","name":"Worn Blades","rarity":"6","children":[{"slug":"weathered-blades","name":"Weathered Blades","rarity":"6","children":[{"slug":"eternal-schism","name":"Eternal Schism","rarity":"7","children":[{"slug":"eternal-sacrifice","name":"Eternal Sacrifice","rarity":"9","children":[],"element":"dragon"}],"element":"dragon"},{"slug":"hi-twin-daggers","name":"Hi Twin Daggers","rarity":"6","children":[{"slug":"silhouette-sabers","name":"Silhouette Sabers","rarity":"7","children":[],"element":"ice"}],"element":"ice"}]}]},{"slug":"rex-slicers","name":"Rex Slicers","rarity":"5","children":[{"slug":"tigrex-claws","name":"Tigrex Claws","rarity":"7","children":[{"slug":"tigrex-claws-plus","name":"Tigrex Claws+","rarity":"10","children":[]}]},{"slug":"hidden-ones","name":"Hidden Ones","rarity":"7","children":[{"slug":"ebony-wings","name":"Ebony Wings","rarity":"10","children":[]}]}]},{"slug":"akantor-blades","name":"Akantor Blades","rarity":"8","children":[{"slug":"akantor-shadow-claws","name":"Akantor Shadow Claws","rarity":"10","children":[]}]},{"slug":"felyne-and-melynx","name":"Felyne and Melynx","rarity":"4","children":[{"slug":"felyne-and-melynx-plus","name":"Felyne and Melynx+","rarity":"9","children":[],"element":"paralysis"}],"element":"paralysis"},{"slug":"ukanlosruinerblades","name":"UkanlosRuinerBlades","rarity":"10","children":[],"element":"ice"},{"slug":"bone-scythe-g","name":"Bone Scythe G","rarity":"9","children":[]},{"slug":"worn-blades-g","name":"Worn Blades G","rarity":"9","children":[]},{"slug":"velociprey-claws-g","name":"Velociprey Claws G","rarity":"9","children":[]},{"slug":"white-death-g","name":"White Death G","rarity":"9","children":[],"element":"ice"},{"slug":"dual-tomahawk-g","name":"Dual Tomahawk G","rarity":"9","children":[]},{"slug":"insector-g","name":"Insector G","rarity":"9","children":[]},{"slug":"glutton-s-set-g","name":"Glutton's Set G","rarity":"9","children":[]},{"slug":"spatula-set-g","name":"Spatula Set G","rarity":"9","children":[]},{"slug":"holy-saber-g","name":"Holy Saber G","rarity":"9","children":[],"element":"water"},{"slug":"cyclone-g","name":"Cyclone G","rarity":"9","children":[]},{"slug":"dual-kut-ku-g","name":"Dual Kut-Ku G","rarity":"9","children":[],"element":"fire"},{"slug":"funky-maracas-g","name":"Funky Maracas G","rarity":"9","children":[]},{"slug":"prototypesaw-slicer-g","name":"PrototypeSaw-Slicr G","rarity":"9","children":[],"element":"thunder"},{"slug":"cutlass-g","name":"Cutlass G","rarity":"9","children":[],"element":"water"},{"slug":"limb-cutter-g","name":"Limb Cutter G","rarity":"9","children":[]},{"slug":"dual-diablo-g","name":"Dual Diablo G","rarity":"9","children":[]},{"slug":"silhouette-sabers-g","name":"Silhouette Sabers G","rarity":"10","children":[],"element":"ice"},{"slug":"gradios-ultimus-g","name":"Gradios Ultimus G","rarity":"10","children":[],"element":"fire"},{"slug":"kirin-bolts-g","name":"Kirin Bolts G","rarity":"10","children":[],"element":"thunder"},{"slug":"crimsonlotusblades-g","name":"CrimsonLotusBlades G","rarity":"10","children":[],"element":"dragon"},{"slug":"dualdragonultimus-g","name":"DualDragonUltimus G","rarity":"10","children":[],"element":"dragon"},{"slug":"legendary-blades-g","name":"Legendary Blades G","rarity":"10","children":[]}]
}
