{
  "name": "Kelbi",
  "drops": {
    "Low-Rank": {
      "Body Carves (x1)": [
        {
          "name": "Kelbi Horn",
          "chance": "50%"
        },
        {
          "name": "Kelbi Hide",
          "chance": "32%"
        },
        {
          "name": "White Liver",
          "chance": "15%"
        },
        {
          "name": "Raw Meat",
          "chance": "3%"
        }
      ]
    },
    "High-Rank": {
      "Body Carves (x1)": [
        {
          "name": "Kelbi Horn",
          "chance": "35%"
        },
        {
          "name": "High Qualty Pelt",
          "chance": "25%"
        },
        {
          "name": "Kelbi Hide",
          "chance": "22%"
        },
        {
          "name": "White Liver",
          "chance": "15%"
        },
        {
          "name": "Raw Meat",
          "chance": "3%"
        }
      ]
    },
    "G-Rank": {
      "Body Carves (x1)": [
        {
          "name": "Kelbi Horn",
          "chance": "35%"
        },
        {
          "name": "High Qualty Pelt",
          "chance": "35%"
        },
        {
          "name": "Kelbi Hide",
          "chance": "17%"
        },
        {
          "name": "White Liver",
          "chance": "10%"
        },
        {
          "name": "Raw Meat",
          "chance": "3%"
        }
      ]
    }
  }
}